genetic_algorithm/__init__.py
genetic_algorithm/algorithms.py
genetic_algorithm/functions.py
genetic_algorithm/core/__init__.py
genetic_algorithm/core/crossover.py
genetic_algorithm/core/fitness.py
genetic_algorithm/core/mutation.py
genetic_algorithm/core/population.py
genetic_algorithm/core/selection.py
genetic_algorithm/problems/__init__.py
genetic_algorithm/problems/combinatorial.py
genetic_algorithm/problems/continuous.py
genetic_algorithm/problems/discrete.py
genetic_algorithm/utils/__init__.py
genetic_algorithm/utils/helpers.py
genetic_algorithm/utils/visualization.py
genetic_algorithm_library-0.2.0.dist-info/METADATA
genetic_algorithm_library-0.2.0.dist-info/WHEEL
genetic_algorithm_library-0.2.0.dist-info/top_level.txt
genetic_algorithm_library-0.2.0.dist-info/RECORD
