Metadata-Version: 2.4
Name: genetic_algorithm_library
Version: 0.2.0
Summary: Librería avanzada de algoritmos genéticos adaptativos para problemas de optimización
Home-page: https://github.com/Zaxazgames1/genetic-algorithm-library
Author: Julian Lara, Johan Rojas
Author-email: johansebastianrojasramirez7@gmail.com
Project-URL: Bug Tracker, https://github.com/Zaxazgames1/genetic-algorithm-library/issues
Project-URL: Documentation, https://github.com/Zaxazgames1/genetic-algorithm-library/wiki
Project-URL: Source Code, https://github.com/Zaxazgames1/genetic-algorithm-library
Keywords: genetic algorithm,optimization,evolutionary computation,adaptive algorithms,multi-objective optimization,TSP,permutation
Classifier: Programming Language :: Python :: 3
Classifier: Programming Language :: Python :: 3.6
Classifier: Programming Language :: Python :: 3.7
Classifier: Programming Language :: Python :: 3.8
Classifier: Programming Language :: Python :: 3.9
Classifier: Programming Language :: Python :: 3.10
Classifier: License :: OSI Approved :: MIT License
Classifier: Operating System :: OS Independent
Classifier: Topic :: Scientific/Engineering :: Artificial Intelligence
Classifier: Topic :: Scientific/Engineering :: Mathematics
Classifier: Intended Audience :: Science/Research
Classifier: Intended Audience :: Developers
Classifier: Development Status :: 4 - Beta
Requires-Python: >=3.6
Requires-Dist: numpy>=1.19.0
Requires-Dist: matplotlib>=3.3.0
Requires-Dist: pandas>=1.1.0
Requires-Dist: scipy>=1.5.0
Dynamic: author
Dynamic: author-email
Dynamic: classifier
Dynamic: description
Dynamic: description-content-type
Dynamic: home-page
Dynamic: keywords
Dynamic: project-url
Dynamic: requires-dist
Dynamic: requires-python
Dynamic: summary
